auth_office365_lbx_v2/__init__.py
auth_office365_lbx_v2/auth.py
auth_office365_lbx_v2-1.3.dist-info/METADATA
auth_office365_lbx_v2-1.3.dist-info/WHEEL
auth_office365_lbx_v2-1.3.dist-info/top_level.txt
auth_office365_lbx_v2-1.3.dist-info/RECORD
