Metadata-Version: 2.1
Name: auth_office365_lbx_v2
Version: 1.3
Summary: Biblioteca para autenticação e verificação de grupos no Office 365
Author: Cristiano P. Ferrari
Author-email: boxferrari@gmail.com
Classifier: Programming Language :: Python :: 3
Classifier: License :: OSI Approved :: MIT License
Classifier: Operating System :: OS Independent
Requires-Python: >=3.6
Requires-Dist: msal
Requires-Dist: requests
Requires-Dist: selenium
Requires-Dist: webdriver-manager
